pysurvival/.DS_Store
pysurvival/__init__.py
pysurvival/cpp_extensions/_coxph.cpp
pysurvival/cpp_extensions/_coxph.pyx
pysurvival/cpp_extensions/_functions.cpp
pysurvival/cpp_extensions/_functions.pyx
pysurvival/cpp_extensions/_metrics.cpp
pysurvival/cpp_extensions/_metrics.pyx
pysurvival/cpp_extensions/_non_parametric.cpp
pysurvival/cpp_extensions/_non_parametric.pyx
pysurvival/cpp_extensions/_survival_forest.cpp
pysurvival/cpp_extensions/_survival_forest.pyx
pysurvival/cpp_extensions/_svm.cpp
pysurvival/cpp_extensions/_svm.pyx
pysurvival/cpp_extensions/functions.cpp
pysurvival/cpp_extensions/functions.h
pysurvival/cpp_extensions/metrics.cpp
pysurvival/cpp_extensions/metrics.h
pysurvival/cpp_extensions/non_parametric.cpp
pysurvival/cpp_extensions/non_parametric.h
pysurvival/cpp_extensions/survival_forest.cpp
pysurvival/cpp_extensions/survival_forest.h
pysurvival/cpp_extensions/survival_forest_data.cpp
pysurvival/cpp_extensions/survival_forest_data.h
pysurvival/cpp_extensions/survival_forest_globals.h
pysurvival/cpp_extensions/survival_forest_tree.cpp
pysurvival/cpp_extensions/survival_forest_tree.h
pysurvival/cpp_extensions/survival_forest_utility.cpp
pysurvival/cpp_extensions/survival_forest_utility.h
pysurvival/datasets/__init__.py
pysurvival/datasets/churn.csv
pysurvival/datasets/credit_risk.csv
pysurvival/datasets/employee_attrition.csv
pysurvival/datasets/maintenance.csv
pysurvival/datasets/simple_example.csv
pysurvival/models/__init__.py
pysurvival/models/_coxph.cpython-37m-darwin.so
pysurvival/models/_non_parametric.cpython-37m-darwin.so
pysurvival/models/_survival_forest.cpython-37m-darwin.so
pysurvival/models/_svm.cpython-37m-darwin.so
pysurvival/models/multi_task.py
pysurvival/models/non_parametric.py
pysurvival/models/parametric.py
pysurvival/models/semi_parametric.py
pysurvival/models/simulations.py
pysurvival/models/survival_forest.py
pysurvival/models/svm.py
pysurvival/utils/__init__.py
pysurvival/utils/_functions.cpython-37m-darwin.so
pysurvival-0.1.2.dist-info/LICENSE.txt
pysurvival-0.1.2.dist-info/METADATA
pysurvival-0.1.2.dist-info/WHEEL
pysurvival-0.1.2.dist-info/top_level.txt
pysurvival-0.1.2.dist-info/RECORD
