Metadata-Version: 2.1
Name: pysurvival
Version: 0.1.2
Summary: Open source package for Survival Analysis modeling
Home-page: https://www.pysurvival.io
Author: steph-likes-git
Author-email: stephane@squareup.com
License: Apache Software License (Apache 2.0)
Platform: UNKNOWN
Classifier: Intended Audience :: Developers
Classifier: Intended Audience :: Education
Classifier: Intended Audience :: Science/Research
Classifier: Operating System :: MacOS
Classifier: Operating System :: Unix
Classifier: Programming Language :: Python :: 2
Classifier: Programming Language :: Python :: 2.7
Classifier: Programming Language :: Python :: 3
Classifier: Programming Language :: Python :: 3.7
Classifier: Topic :: Scientific/Engineering
Classifier: Topic :: Scientific/Engineering :: Mathematics
Classifier: Topic :: Scientific/Engineering :: Artificial Intelligence
Classifier: Topic :: Software Development
Classifier: Topic :: Software Development :: Libraries :: Python Modules
Requires-Dist: matplotlib
Requires-Dist: numpy
Requires-Dist: pandas
Requires-Dist: pip
Requires-Dist: progressbar
Requires-Dist: pyarrow
Requires-Dist: scikit-learn
Requires-Dist: scipy
Requires-Dist: sklearn
Requires-Dist: torch
Provides-Extra: tests
Requires-Dist: pytest ; extra == 'tests'
Requires-Dist: pytest-pep8 ; extra == 'tests'
